megabot9/__init__.py
megabot9/address.py
megabot9/address_book.py
megabot9/birthday.py
megabot9/boterror.py
megabot9/decorators.py
megabot9/email.py
megabot9/field.py
megabot9/handler.py
megabot9/main.py
megabot9/name.py
megabot9/note.py
megabot9/note_book.py
megabot9/phone.py
megabot9/record.py
megabot9/session_handler.py
megabot9/texts.py
megabot9/utils.py
megabot9-1.0.7.dist-info/LICENSE
megabot9-1.0.7.dist-info/METADATA
megabot9-1.0.7.dist-info/WHEEL
megabot9-1.0.7.dist-info/entry_points.txt
megabot9-1.0.7.dist-info/top_level.txt
megabot9-1.0.7.dist-info/RECORD
